simple_cisco_support_api/__init__.py
simple_cisco_support_api/rest_client/LICENSE
simple_cisco_support_api/rest_client/README
simple_cisco_support_api/rest_client/__init__.py
simple_cisco_support_api/rest_client/api.py
simple_cisco_support_api/rest_client/curlify.py
simple_cisco_support_api/rest_client/decorators.py
simple_cisco_support_api/rest_client/exceptions.py
simple_cisco_support_api/rest_client/models.py
simple_cisco_support_api/rest_client/request.py
simple_cisco_support_api/rest_client/resource.py
simple_cisco_support_api-0.1.dist-info/LICENSE
simple_cisco_support_api-0.1.dist-info/METADATA
simple_cisco_support_api-0.1.dist-info/WHEEL
simple_cisco_support_api-0.1.dist-info/top_level.txt
simple_cisco_support_api-0.1.dist-info/RECORD
