Metadata-Version: 2.1
Name: simple-cisco-support-api
Version: 0.1
Summary: Simple REST-client for Cisco Support API
Home-page: https://github.com/jinjamator/simple_cisco_support_api
Author: Wilhelm Putz
Author-email: wilhelm.putz@cancom.com
License: ASL V2
Platform: UNKNOWN
Classifier: License :: OSI Approved :: Apache Software License
Classifier: Programming Language :: Python :: 3.7
Classifier: Programming Language :: Python :: 3.8
Classifier: Topic :: System :: Installation/Setup
Classifier: Topic :: System :: Systems Administration
Classifier: Topic :: Utilities
Requires-Python: >=3.7
License-File: LICENSE
Requires-Dist: httpx
